{
  "school_to_gemstones": {
    "arcane": ["Tanzanite"],
    "water": ["Apatite", "Aquamarine"],
    "ice": ["Apatite", "Aquamarine", "Sapphire"],
    "fire": ["Carnelian", "Ruby", "Topaz"],
    "blood": ["Carnelian", "Ruby"],
    "light": ["Citrine", "Topaz"],
    "thunder": ["Citrine", "Topaz"],
    "air": ["Moonstone"],
    "nature": ["Jade", "Peridot"],
    "earth": ["Hematite", "Jade", "Peridot"],
    "dark": ["Hematite", "Sodalite"],
    "void": ["Hematite", "Tanzanite"],
    "chaos": ["Rhodonite", "Tourmaline"]
  },
  "ritual_to_gemstones": {
    "temporal": ["Moonstone"],
    "planar": ["Tanzanite"],
    "vortex": ["Apatite", "Sodalite"],
    "fountain": ["Apatite", "Aquamarine"],
    "sacrifice": ["Carnelian", "Hematite", "Ruby"],
    "ascension": ["Citrine", "Topaz"],
    "resurrection": ["Citrine", "Rhodonite"],
    "circle": ["Moonstone"],
    "reality": ["Tourmaline"],
    "elemental": ["Ruby", "Sapphire", "Tourmaline"],
    "summoning": ["Hematite", "Sodalite", "Tanzanite"],
    "transformation": ["Jade", "Peridot", "Tourmaline"],
    "cosmic": ["Moonstone", "Sapphire", "Tanzanite"]
  },
  "gemstone_to_schools": {
    "Amethyst Shard": ["arcane"],
    "Apatite": ["water", "ice"],
    "Aquamarine": ["water", "ice"],
    "Carnelian": ["fire", "blood"],
    "Citrine": ["light", "thunder"],
    "Hematite": ["earth", "dark", "void"],
    "Jade": ["nature", "earth"],
    "Moonstone": ["air"],
    "Peridot": ["nature", "earth"],
    "Rhodonite": ["chaos"],
    "Ruby": ["fire", "blood"],
    "Sapphire": ["ice"],
    "Sodalite": ["dark"],
    "Tanzanite": ["void", "arcane"],
    "Topaz": ["light", "thunder", "fire"],
    "Tourmaline": ["chaos"]
  },
  "gemstone_to_rituals": {
    "Apatite": ["vortex", "fountain"],
    "Aquamarine": ["fountain"],
    "Carnelian": ["sacrifice"],
    "Citrine": ["ascension", "resurrection"],
    "Hematite": ["sacrifice", "summoning"],
    "Jade": ["transformation"],
    "Moonstone": ["circle", "cosmic", "temporal"],
    "Peridot": ["transformation"],
    "Rhodonite": ["resurrection"],
    "Ruby": ["elemental", "sacrifice"],
    "Sapphire": ["elemental", "cosmic"],
    "Sodalite": ["summoning", "vortex"],
    "Tanzanite": ["planar", "cosmic", "summoning"],
    "Topaz": ["ascension"],
    "Tourmaline": ["elemental", "reality", "transformation"]
  },
  "rarity_distribution": {
    "epic": ["Ruby", "Sapphire", "Tanzanite"],
    "rare": [
      "Apatite",
      "Aquamarine",
      "Moonstone",
      "Rhodonite",
      "Topaz",
      "Tourmaline"
    ],
    "uncommon": ["Carnelian", "Citrine", "Jade", "Peridot", "Sodalite"],
    "common": ["Hematite"]
  }
}
